.gitignore
MANIFEST.in
README.rst
bootstrap.py
buildout.cfg
collective.fancyboxgallery-configure.zcml
setup.py
collective/__init__.py
collective.fancyboxgallery.egg-info/PKG-INFO
collective.fancyboxgallery.egg-info/SOURCES.txt
collective.fancyboxgallery.egg-info/dependency_links.txt
collective.fancyboxgallery.egg-info/entry_points.txt
collective.fancyboxgallery.egg-info/namespace_packages.txt
collective.fancyboxgallery.egg-info/not-zip-safe
collective.fancyboxgallery.egg-info/requires.txt
collective.fancyboxgallery.egg-info/top_level.txt
collective/fancyboxgallery/__init__.py
collective/fancyboxgallery/configure.zcml
collective/fancyboxgallery/i18n.py
collective/fancyboxgallery/rebuild_i18n.sh
collective/fancyboxgallery/upgrades.py
collective/fancyboxgallery/vocabulary.py
collective/fancyboxgallery/browser/__init__.py
collective/fancyboxgallery/browser/configure.zcml
collective/fancyboxgallery/browser/fancybox.pt
collective/fancyboxgallery/browser/fancybox.py
collective/fancyboxgallery/browser/interfaces.py
collective/fancyboxgallery/locales/collective.fancyboxgallery.pot
collective/fancyboxgallery/locales/en/LC_MESSAGES/collective.fancyboxgallery.po
collective/fancyboxgallery/locales/fr/LC_MESSAGES/collective.fancyboxgallery.po
collective/fancyboxgallery/profiles/default/browserlayer.xml
collective/fancyboxgallery/profiles/default/metadata.xml
collective/fancyboxgallery/profiles/default/types/Folder.xml
collective/fancyboxgallery/profiles/default/types/Link.xml
collective/fancyboxgallery/profiles/default/types/Topic.xml
collective/fancyboxgallery/tests/__init__.py
collective/fancyboxgallery/tests/base.py
collective/fancyboxgallery/tests/layer.py
collective/fancyboxgallery/tests/test_setup.py
docs/HISTORY.txt