Metadata-Version: 1.0
Name: collective.fancyboxgallery
Version: 1.0
Summary: Gallery view for Plone using jquery.fancybox
Home-page: https://github.com/toutpt/collective.fancyboxgallery
Author: JeanMichel FRANCOIS
Author-email: toutpt@gmail.com
License: GPL
Keywords: plone fancybox
Platform: UNKNOWN
Classifier: Programming Language :: Python
Classifier: Framework :: Plone
Classifier: Framework :: Plone :: 4.0
Classifier: Framework :: Plone :: 4.1
Classifier: Framework :: Plone :: 4.2
